MANIFEST.in
README.txt
setup.py
pyneurgen/.todo.kate-swp
pyneurgen/Makefile
pyneurgen/__init__.py
pyneurgen/fitness.py
pyneurgen/genotypes.py
pyneurgen/grammatical_evolution.py
pyneurgen/layers.py
pyneurgen/neuralnet.py
pyneurgen/nodes.py
pyneurgen/recurrent.py
pyneurgen/utilities.py
pyneurgen.egg-info/PKG-INFO
pyneurgen.egg-info/SOURCES.txt
pyneurgen.egg-info/dependency_links.txt
pyneurgen.egg-info/top_level.txt
pyneurgen/demo/.directory
pyneurgen/demo/sample_grammatical_evolution.py
pyneurgen/demo/sample_neural_genetic.py
pyneurgen/demo/simple_network_with_graphs.py
pyneurgen/docs/authors.txt
pyneurgen/docs/changelog.txt
pyneurgen/docs/install.txt
pyneurgen/docs/license.txt
pyneurgen/docs/thanks.txt
pyneurgen/docs/todo.txt
pyneurgen/docs/html/fitness_functions.html
pyneurgen/docs/html/ge_suggestions.html
pyneurgen/docs/html/grammatical_evolution.html
pyneurgen/docs/html/index.html
pyneurgen/docs/html/neural_networks.html
pyneurgen/docs/html/nn_suggestions.html
pyneurgen/docs/html/recurrent.html
pyneurgen/docs/html/resources.html
pyneurgen/docs/html/tutorial_ge.html
pyneurgen/docs/html/tutorial_genn.html
pyneurgen/docs/html/tutorial_nn.html
pyneurgen/docs/html/api/fitness_api.html
pyneurgen/docs/html/api/genotypes_api.html
pyneurgen/docs/html/api/grammatical_evolution_api.html
pyneurgen/docs/html/api/index.html
pyneurgen/docs/html/api/layers_api.html
pyneurgen/docs/html/api/neuralnet_api.html
pyneurgen/docs/html/api/nodes_api.html
pyneurgen/docs/html/api/recurrent_api.html
pyneurgen/docs/html/api/utilities_api.html
pyneurgen/docs/html/static/codehilite.css
pyneurgen/docs/html/static/style.css
pyneurgen/docs/html/static/images/NARX2.png
pyneurgen/docs/html/static/images/elman_srn2.png
pyneurgen/docs/html/static/images/genn_fitness.png
pyneurgen/docs/html/static/images/genn_results.png
pyneurgen/docs/html/static/images/jordan_nn2.png
pyneurgen/docs/html/static/images/menu.png
pyneurgen/docs/html/static/images/neuron-heading.png
pyneurgen/docs/html/static/images/nn_mse_epochs.png
pyneurgen/docs/html/static/images/nn_population.png
pyneurgen/docs/html/static/images/nn_target_actuals.png
