Metadata-Version: 1.0
Name: pyneurgen
Version: 0.3.0
Summary: Python Neural Genetic Hybrids
Home-page: http://pyneurgen/sourceforge.net
Author: Don Smiley
Author-email: ds@sidorof.com
License: GPL
Keywords: grammatical evolution programming neural networks genetic algorithms
Platform: UNKNOWN
Classifier: Development Status :: 3 - Alpha
Classifier: Environment :: Console
Classifier: Intended Audience :: Developers
Classifier: Intended Audience :: Science/Research
Classifier: License :: OSI Approved :: GNU General Public License (GPL)
Classifier: Natural Language :: English
Classifier: Operating System :: OS Independent
Classifier: Programming Language :: Python :: 2.6
Classifier: Programming Language :: Python :: 2.7
Classifier: Topic :: Adaptive Technologies
Classifier: Topic :: Scientific/Engineering :: Artificial Intelligence
Classifier: Topic :: Scientific/Engineering :: Bio-Informatics
Classifier: Topic :: Scientific/Engineering :: Mathematics
Classifier: Topic :: Software Development :: Libraries :: Python Modules
